{"annotation": {"filename": "imagem-116.jpg", "folder": "segmentation_xray", "source": {"sourceImage": "The MIT-CSAIL database of objects and scenes", "sourceAnnotation": "LabelMe Webtool"}, "object": [{"name": "tooth", "deleted": "0", "verified": "0", "occluded": "no", "attributes": "18", "parts": {"hasparts": null, "ispartof": null}, "date": "12-05-21 11:10:53:963", "id": "0", "type": "bounding_box", "polygon": {"username": "anonymous", "pt": [{"x": "130", "y": "4", "time": "12-05-21 11:10:44:430"}, {"x": "522", "y": "4", "time": "12-05-21 11:10:47:303"}, {"x": "522", "y": "542", "time": "undefined"}, {"x": "130", "y": "542", "time": "undefined"}], "closed_date": "12-05-21 11:10:47:303"}}, {"name": "tooth", "deleted": "0", "verified": "0", "occluded": "no", "attributes": "17", "parts": {"hasparts": "2", "ispartof": null}, "date": "12-05-21 11:11:20:248", "id": "1", "type": "bounding_box", "polygon": {"username": "anonymous", "pt": [{"x": "915", "y": "581", "time": "12-05-21 11:11:09:419"}, {"x": "497", "y": "581", "time": "12-05-21 11:11:12:676"}, {"x": "497", "y": "12", "time": "undefined"}, {"x": "915", "y": "12", "time": "undefined"}], "closed_date": "12-05-21 11:11:12:676"}}, {"name": "restoration", "deleted": "0", "verified": "0", "occluded": "no", "attributes": null, "parts": {"hasparts": null, "ispartof": "1"}, "date": "12-05-21 11:11:52:192", "id": "2", "polygon": {"username": "anonymous", "pt": [{"x": "558", "y": "432", "time": "12-05-21 11:11:33:790"}, {"x": "595", "y": "452", "time": "12-05-21 11:11:34:463"}, {"x": "626", "y": "465", "time": "12-05-21 11:11:34:991"}, {"x": "658", "y": "465", "time": "12-05-21 11:11:35:478"}, {"x": "679", "y": "465", "time": "12-05-21 11:11:35:991"}, {"x": "691", "y": "448", "time": "12-05-21 11:11:36:616"}, {"x": "715", "y": "448", "time": "12-05-21 11:11:37:077"}, {"x": "721", "y": "458", "time": "12-05-21 11:11:37:583"}, {"x": "719", "y": "465", "time": "12-05-21 11:11:38:113"}, {"x": "719", "y": "469", "time": "12-05-21 11:11:38:624"}, {"x": "736", "y": "479", "time": "12-05-21 11:11:39:193"}, {"x": "793", "y": "473", "time": "12-05-21 11:11:39:680"}, {"x": "813", "y": "458", "time": "12-05-21 11:11:40:363"}, {"x": "831", "y": "509", "time": "12-05-21 11:11:40:834"}, {"x": "844", "y": "536", "time": "12-05-21 11:11:41:583"}, {"x": "829", "y": "542", "time": "12-05-21 11:11:42:046"}, {"x": "770", "y": "558", "time": "12-05-21 11:11:42:655"}, {"x": "727", "y": "571", "time": "12-05-21 11:11:43:312"}, {"x": "695", "y": "558", "time": "12-05-21 11:11:43:879"}, {"x": "638", "y": "554", "time": "12-05-21 11:11:44:451"}, {"x": "575", "y": "542", "time": "12-05-21 11:11:45:012"}, {"x": "536", "y": "520", "time": "12-05-21 11:11:45:483"}, {"x": "522", "y": "487", "time": "12-05-21 11:11:46:084"}, {"x": "520", "y": "473", "time": "12-05-21 11:11:46:604"}, {"x": "544", "y": "454", "time": "12-05-21 11:11:47:149"}], "closed_date": "12-05-21 11:11:47:675"}}, {"name": "tooth", "deleted": "0", "verified": "0", "occluded": "no", "attributes": "16", "parts": {"hasparts": "4", "ispartof": null}, "date": "12-05-21 11:18:01:883", "id": "3", "type": "bounding_box", "polygon": {"username": "anonymous", "pt": [{"x": "1316", "y": "597", "time": "12-05-21 11:17:52:651"}, {"x": "833", "y": "597", "time": "12-05-21 11:17:56:087"}, {"x": "833", "y": "16", "time": "undefined"}, {"x": "1316", "y": "16", "time": "undefined"}], "closed_date": "12-05-21 11:17:56:087"}}, {"name": "restoration", "deleted": "0", "verified": "0", "occluded": "no", "attributes": null, "parts": {"hasparts": null, "ispartof": "3"}, "date": "12-05-21 11:18:40:606", "id": "4", "polygon": {"username": "anonymous", "pt": [{"x": "933", "y": "475", "time": "12-05-21 11:18:21:620"}, {"x": "996", "y": "483", "time": "12-05-21 11:18:22:253"}, {"x": "1056", "y": "483", "time": "12-05-21 11:18:22:862"}, {"x": "1070", "y": "473", "time": "12-05-21 11:18:23:439"}, {"x": "1115", "y": "473", "time": "12-05-21 11:18:23:952"}, {"x": "1166", "y": "479", "time": "12-05-21 11:18:24:497"}, {"x": "1214", "y": "491", "time": "12-05-21 11:18:25:040"}, {"x": "1221", "y": "505", "time": "12-05-21 11:18:25:877"}, {"x": "1198", "y": "505", "time": "12-05-21 11:18:26:405"}, {"x": "1194", "y": "524", "time": "12-05-21 11:18:26:966"}, {"x": "1155", "y": "540", "time": "12-05-21 11:18:27:771"}, {"x": "1113", "y": "540", "time": "12-05-21 11:18:28:437"}, {"x": "1080", "y": "542", "time": "12-05-21 11:18:29:006"}, {"x": "1066", "y": "524", "time": "12-05-21 11:18:29:640"}, {"x": "1051", "y": "524", "time": "12-05-21 11:18:30:192"}, {"x": "1049", "y": "536", "time": "12-05-21 11:18:30:744"}, {"x": "1037", "y": "540", "time": "12-05-21 11:18:31:346"}, {"x": "1009", "y": "538", "time": "12-05-21 11:18:31:866"}, {"x": "992", "y": "538", "time": "12-05-21 11:18:32:386"}, {"x": "931", "y": "528", "time": "12-05-21 11:18:33:223"}, {"x": "903", "y": "520", "time": "12-05-21 11:18:34:069"}, {"x": "903", "y": "495", "time": "12-05-21 11:18:34:694"}, {"x": "915", "y": "477", "time": "12-05-21 11:18:35:376"}], "closed_date": "12-05-21 11:18:36:051"}}, {"name": "tooth", "deleted": "0", "verified": "0", "occluded": "no", "attributes": "15", "parts": {"hasparts": "6", "ispartof": null}, "date": "12-05-21 11:18:58:818", "id": "5", "type": "bounding_box", "polygon": {"username": "anonymous", "pt": [{"x": "1577", "y": "593", "time": "12-05-21 11:18:46:178"}, {"x": "1265", "y": "593", "time": "12-05-21 11:18:50:476"}, {"x": "1265", "y": "10", "time": "undefined"}, {"x": "1577", "y": "10", "time": "undefined"}], "closed_date": "12-05-21 11:18:50:476"}}, {"name": "restoration", "deleted": "0", "verified": "0", "occluded": "no", "attributes": null, "parts": {"hasparts": null, "ispartof": "5"}, "date": "12-05-21 11:19:50:780", "id": "6", "polygon": {"username": "anonymous", "pt": [{"x": "1496", "y": "458", "time": "12-05-21 11:19:25:073"}, {"x": "1441", "y": "456", "time": "12-05-21 11:19:25:925"}, {"x": "1433", "y": "456", "time": "12-05-21 11:19:32:353"}, {"x": "1412", "y": "456", "time": "12-05-21 11:19:33:190"}, {"x": "1422", "y": "430", "time": "12-05-21 11:19:33:937"}, {"x": "1412", "y": "389", "time": "12-05-21 11:19:34:563"}, {"x": "1388", "y": "371", "time": "12-05-21 11:19:35:108"}, {"x": "1359", "y": "371", "time": "12-05-21 11:19:35:668"}, {"x": "1331", "y": "379", "time": "12-05-21 11:19:36:245"}, {"x": "1306", "y": "397", "time": "12-05-21 11:19:36:728"}, {"x": "1286", "y": "416", "time": "12-05-21 11:19:37:415"}, {"x": "1286", "y": "430", "time": "12-05-21 11:19:38:008"}, {"x": "1292", "y": "501", "time": "12-05-21 11:19:38:602"}, {"x": "1298", "y": "511", "time": "12-05-21 11:19:39:114"}, {"x": "1345", "y": "532", "time": "12-05-21 11:19:39:748"}, {"x": "1349", "y": "546", "time": "12-05-21 11:19:40:585"}, {"x": "1390", "y": "536", "time": "12-05-21 11:19:41:094"}, {"x": "1441", "y": "530", "time": "12-05-21 11:19:41:747"}, {"x": "1481", "y": "530", "time": "12-05-21 11:19:42:219"}, {"x": "1514", "y": "522", "time": "12-05-21 11:19:42:747"}, {"x": "1516", "y": "493", "time": "12-05-21 11:19:43:292"}, {"x": "1518", "y": "471", "time": "12-05-21 11:19:43:882"}, {"x": "1518", "y": "471", "time": "12-05-21 11:19:44:104"}, {"x": "1518", "y": "471", "time": "12-05-21 11:19:44:396"}], "closed_date": "12-05-21 11:19:45:356"}}, {"name": "tooth", "deleted": "0", "verified": "0", "occluded": "no", "attributes": "48", "parts": {"hasparts": null, "ispartof": null}, "date": "12-05-21 11:20:20:745", "id": "7", "type": "bounding_box", "polygon": {"username": "anonymous", "pt": [{"x": "177", "y": "1235", "time": "12-05-21 11:20:02:131"}, {"x": "648", "y": "1235", "time": "12-05-21 11:20:08:891"}, {"x": "648", "y": "589", "time": "undefined"}, {"x": "177", "y": "589", "time": "undefined"}], "closed_date": "12-05-21 11:20:08:892"}}, {"name": "tooth", "deleted": "0", "verified": "0", "occluded": "no", "attributes": "47", "parts": {"hasparts": "11", "ispartof": null}, "date": "12-05-21 11:20:47:661", "id": "8", "type": "bounding_box", "polygon": {"username": "anonymous", "pt": [{"x": "1094", "y": "1241", "time": "12-05-21 11:20:33:347"}, {"x": "617", "y": "1241", "time": "12-05-21 11:20:38:588"}, {"x": "617", "y": "679", "time": "undefined"}, {"x": "1094", "y": "679", "time": "undefined"}], "closed_date": "12-05-21 11:20:38:588"}}, {"name": "restoration", "deleted": "1", "verified": "0", "occluded": "no", "attributes": null, "parts": {"hasparts": null, "ispartof": null}, "date": "12-05-21 11:21:52:046", "id": "9", "polygon": {"username": "anonymous", "pt": [{"x": "752", "y": "709", "time": "12-05-21 11:21:30:438"}, {"x": "819", "y": "717", "time": "12-05-21 11:21:31:234"}, {"x": "846", "y": "711", "time": "12-05-21 11:21:32:045"}, {"x": "868", "y": "723", "time": "12-05-21 11:21:32:771"}, {"x": "901", "y": "723", "time": "12-05-21 11:21:33:330"}, {"x": "943", "y": "723", "time": "12-05-21 11:21:33:875"}, {"x": "990", "y": "738", "time": "12-05-21 11:21:34:639"}, {"x": "1019", "y": "762", "time": "12-05-21 11:21:35:395"}, {"x": "1039", "y": "778", "time": "12-05-21 11:21:36:053"}, {"x": "1045", "y": "789", "time": "12-05-21 11:21:36:712"}, {"x": "1049", "y": "817", "time": "12-05-21 11:21:37:427"}, {"x": "1049", "y": "837", "time": "12-05-21 11:21:38:168"}, {"x": "1023", "y": "858", "time": "12-05-21 11:21:38:995"}, {"x": "982", "y": "868", "time": "12-05-21 11:21:39:913"}, {"x": "945", "y": "866", "time": "12-05-21 11:21:40:466"}, {"x": "905", "y": "866", "time": "12-05-21 11:21:41:189"}, {"x": "886", "y": "868", "time": "12-05-21 11:21:41:888"}, {"x": "858", "y": "852", "time": "12-05-21 11:21:42:458"}, {"x": "837", "y": "829", "time": "12-05-21 11:21:43:067"}, {"x": "797", "y": "829", "time": "12-05-21 11:21:43:563"}, {"x": "732", "y": "811", "time": "12-05-21 11:21:44:407"}, {"x": "707", "y": "785", "time": "12-05-21 11:21:45:116"}, {"x": "699", "y": "766", "time": "12-05-21 11:21:45:749"}, {"x": "699", "y": "738", "time": "12-05-21 11:21:46:303"}, {"x": "699", "y": "719", "time": "12-05-21 11:21:46:838"}, {"x": "729", "y": "711", "time": "12-05-21 11:21:47:342"}], "closed_date": "12-05-21 11:21:47:846"}}, {"name": "tooth", "deleted": "0", "verified": "0", "occluded": "no", "attributes": "46", "parts": {"hasparts": "12", "ispartof": null}, "date": "12-05-21 11:22:08:746", "id": "10", "type": "bounding_box", "polygon": {"username": "anonymous", "pt": [{"x": "1565", "y": "703", "time": "12-05-21 11:22:00:232"}, {"x": "1088", "y": "703", "time": "12-05-21 11:22:03:457"}, {"x": "1088", "y": "1239", "time": "undefined"}, {"x": "1565", "y": "1239", "time": "undefined"}], "closed_date": "12-05-21 11:22:03:458"}}, {"name": "restoration", "deleted": "0", "verified": "0", "occluded": "no", "attributes": null, "parts": {"hasparts": null, "ispartof": "8"}, "date": "12-05-21 11:23:13:416", "id": "11", "polygon": {"username": "anonymous", "pt": [{"x": "705", "y": "734", "time": "12-05-21 11:22:56:612"}, {"x": "705", "y": "782", "time": "12-05-21 11:22:57:440"}, {"x": "736", "y": "807", "time": "12-05-21 11:22:58:220"}, {"x": "835", "y": "829", "time": "12-05-21 11:22:59:015"}, {"x": "864", "y": "850", "time": "12-05-21 11:22:59:708"}, {"x": "897", "y": "866", "time": "12-05-21 11:23:00:413"}, {"x": "964", "y": "874", "time": "12-05-21 11:23:00:991"}, {"x": "1037", "y": "850", "time": "12-05-21 11:23:01:666"}, {"x": "1053", "y": "837", "time": "12-05-21 11:23:02:308"}, {"x": "1056", "y": "807", "time": "12-05-21 11:23:02:990"}, {"x": "1027", "y": "764", "time": "12-05-21 11:23:03:640"}, {"x": "984", "y": "734", "time": "12-05-21 11:23:04:364"}, {"x": "945", "y": "717", "time": "12-05-21 11:23:04:954"}, {"x": "895", "y": "729", "time": "12-05-21 11:23:05:509"}, {"x": "864", "y": "725", "time": "12-05-21 11:23:06:087"}, {"x": "837", "y": "707", "time": "12-05-21 11:23:06:770"}, {"x": "817", "y": "709", "time": "12-05-21 11:23:07:460"}, {"x": "776", "y": "709", "time": "12-05-21 11:23:07:997"}, {"x": "734", "y": "709", "time": "12-05-21 11:23:08:523"}, {"x": "719", "y": "711", "time": "12-05-21 11:23:09:067"}], "closed_date": "12-05-21 11:23:09:631"}}, {"name": "restoration", "deleted": "0", "verified": "0", "occluded": "no", "attributes": null, "parts": {"hasparts": null, "ispartof": "10"}, "date": "12-05-21 11:23:43:445", "id": "12", "polygon": {"username": "anonymous", "pt": [{"x": "1286", "y": "776", "time": "12-05-21 11:23:22:270"}, {"x": "1320", "y": "732", "time": "12-05-21 11:23:23:226"}, {"x": "1369", "y": "727", "time": "12-05-21 11:23:23:854"}, {"x": "1402", "y": "723", "time": "12-05-21 11:23:24:463"}, {"x": "1437", "y": "719", "time": "12-05-21 11:23:25:138"}, {"x": "1467", "y": "721", "time": "12-05-21 11:23:25:690"}, {"x": "1485", "y": "752", "time": "12-05-21 11:23:26:324"}, {"x": "1496", "y": "791", "time": "12-05-21 11:23:26:958"}, {"x": "1473", "y": "801", "time": "12-05-21 11:23:27:535"}, {"x": "1447", "y": "807", "time": "12-05-21 11:23:28:047"}, {"x": "1424", "y": "807", "time": "12-05-21 11:23:28:591"}, {"x": "1410", "y": "817", "time": "12-05-21 11:23:29:340"}, {"x": "1386", "y": "840", "time": "12-05-21 11:23:30:518"}, {"x": "1402", "y": "866", "time": "12-05-21 11:23:31:371"}, {"x": "1398", "y": "899", "time": "12-05-21 11:23:32:184"}, {"x": "1380", "y": "919", "time": "12-05-21 11:23:32:940"}, {"x": "1351", "y": "919", "time": "12-05-21 11:23:33:508"}, {"x": "1312", "y": "913", "time": "12-05-21 11:23:34:460"}, {"x": "1310", "y": "886", "time": "12-05-21 11:23:35:077"}, {"x": "1288", "y": "868", "time": "12-05-21 11:23:35:809"}, {"x": "1288", "y": "854", "time": "12-05-21 11:23:36:361"}, {"x": "1302", "y": "835", "time": "12-05-21 11:23:37:150"}, {"x": "1302", "y": "833", "time": "12-05-21 11:23:37:654"}, {"x": "1292", "y": "831", "time": "12-05-21 11:23:38:271"}, {"x": "1290", "y": "803", "time": "12-05-21 11:23:38:922"}], "closed_date": "12-05-21 11:23:39:678"}}], "imagesize": {"nrows": null, "ncols": null}}}