{"annotation": {"filename": "imagem-018.jpg", "folder": "segmentation_xray", "source": {"sourceImage": "The MIT-CSAIL database of objects and scenes", "sourceAnnotation": "LabelMe Webtool"}, "object": [{"name": "tooth", "deleted": "0", "verified": "0", "occluded": "no", "attributes": "16", "parts": {"hasparts": null, "ispartof": null}, "date": "18-05-21 22:01:13:502", "id": "0", "type": "bounding_box", "polygon": {"username": "anonymous", "pt": [{"x": "1367", "y": "44", "time": "18-05-21 22:00:54:154"}, {"x": "102", "y": "44", "time": "18-05-21 22:00:58:979"}, {"x": "102", "y": "1148", "time": "undefined"}, {"x": "1367", "y": "1148", "time": "undefined"}], "closed_date": "18-05-21 22:00:58:979"}}, {"name": "tooth", "deleted": "0", "verified": "0", "occluded": "no", "attributes": "84", "parts": {"hasparts": null, "ispartof": null}, "date": "18-05-21 22:01:54:297", "id": "1", "type": "bounding_box", "polygon": {"username": "anonymous", "pt": [{"x": "2773", "y": "1381", "time": "18-05-21 22:01:37:712"}, {"x": "3789", "y": "1381", "time": "18-05-21 22:01:42:197"}, {"x": "3789", "y": "2408", "time": "undefined"}, {"x": "2773", "y": "2408", "time": "undefined"}], "closed_date": "18-05-21 22:01:42:197"}}, {"name": "tooth", "deleted": "0", "verified": "0", "occluded": "no", "attributes": "44", "parts": {"hasparts": null, "ispartof": null}, "date": "18-05-21 22:02:22:734", "id": "2", "type": "bounding_box", "polygon": {"username": "anonymous", "pt": [{"x": "2651", "y": "2199", "time": "18-05-21 22:02:09:002"}, {"x": "3629", "y": "2199", "time": "18-05-21 22:02:12:870"}, {"x": "3629", "y": "2641", "time": "undefined"}, {"x": "2651", "y": "2641", "time": "undefined"}], "closed_date": "18-05-21 22:02:12:871"}}, {"name": "tooth", "deleted": "0", "verified": "0", "occluded": "no", "attributes": "85", "parts": {"hasparts": null, "ispartof": null}, "date": "18-05-21 22:02:39:794", "id": "3", "type": "bounding_box", "polygon": {"username": "anonymous", "pt": [{"x": "1557", "y": "1352", "time": "18-05-21 22:02:26:097"}, {"x": "2739", "y": "1352", "time": "18-05-21 22:02:31:300"}, {"x": "2739", "y": "2622", "time": "undefined"}, {"x": "1557", "y": "2622", "time": "undefined"}], "closed_date": "18-05-21 22:02:31:301"}}, {"name": "tooth", "deleted": "0", "verified": "0", "occluded": "no", "attributes": "45", "parts": {"hasparts": null, "ispartof": null}, "date": "18-05-21 22:02:55:437", "id": "4", "type": "bounding_box", "polygon": {"username": "anonymous", "pt": [{"x": "1435", "y": "2281", "time": "18-05-21 22:02:43:077"}, {"x": "2286", "y": "2281", "time": "18-05-21 22:02:46:037"}, {"x": "2286", "y": "2636", "time": "undefined"}, {"x": "1435", "y": "2636", "time": "undefined"}], "closed_date": "18-05-21 22:02:46:037"}}, {"name": "tooth", "deleted": "0", "verified": "0", "occluded": "no", "attributes": "46", "parts": {"hasparts": null, "ispartof": null}, "date": "18-05-21 22:03:12:067", "id": "5", "type": "bounding_box", "polygon": {"username": "anonymous", "pt": [{"x": "141", "y": "1236", "time": "18-05-21 22:03:02:908"}, {"x": "1566", "y": "1236", "time": "18-05-21 22:03:06:671"}, {"x": "1566", "y": "2612", "time": "undefined"}, {"x": "141", "y": "2612", "time": "undefined"}], "closed_date": "18-05-21 22:03:06:671"}}, {"name": "tooth", "deleted": "0", "verified": "0", "occluded": "no", "attributes": "53", "parts": {"hasparts": null, "ispartof": null}, "date": "18-05-21 22:04:23:270", "id": "6", "type": "bounding_box", "polygon": {"username": "anonymous", "pt": [{"x": "3347", "y": "54", "time": "18-05-21 22:04:06:912"}, {"x": "4057", "y": "54", "time": "18-05-21 22:04:08:967"}, {"x": "4057", "y": "1099", "time": "undefined"}, {"x": "3347", "y": "1099", "time": "undefined"}], "closed_date": "18-05-21 22:04:08:968"}}, {"name": "tooth", "deleted": "0", "verified": "0", "occluded": "no", "attributes": "54", "parts": {"hasparts": null, "ispartof": null}, "date": "18-05-21 22:04:37:261", "id": "7", "type": "bounding_box", "polygon": {"username": "anonymous", "pt": [{"x": "2486", "y": "29", "time": "18-05-21 22:04:26:313"}, {"x": "3395", "y": "29", "time": "18-05-21 22:04:29:572"}, {"x": "3395", "y": "1065", "time": "undefined"}, {"x": "2486", "y": "1065", "time": "undefined"}], "closed_date": "18-05-21 22:04:29:573"}}, {"name": "tooth", "deleted": "0", "verified": "0", "occluded": "no", "attributes": "55", "parts": {"hasparts": null, "ispartof": null}, "date": "18-05-21 22:04:50:793", "id": "8", "type": "bounding_box", "polygon": {"username": "anonymous", "pt": [{"x": "1381", "y": "10", "time": "18-05-21 22:04:42:550"}, {"x": "2534", "y": "10", "time": "18-05-21 22:04:44:809"}, {"x": "2534", "y": "1124", "time": "undefined"}, {"x": "1381", "y": "1124", "time": "undefined"}], "closed_date": "18-05-21 22:04:44:809"}}, {"name": "tooth", "deleted": "0", "verified": "0", "occluded": "no", "attributes": "83", "parts": {"hasparts": null, "ispartof": null}, "date": "18-05-21 22:05:10:246", "id": "9", "type": "bounding_box", "polygon": {"username": "anonymous", "pt": [{"x": "3653", "y": "2437", "time": "18-05-21 22:04:54:950"}, {"x": "4081", "y": "2437", "time": "18-05-21 22:04:57:012"}, {"x": "4081", "y": "1381", "time": "undefined"}, {"x": "3653", "y": "1381", "time": "undefined"}], "closed_date": "18-05-21 22:04:57:012"}}], "imagesize": {"nrows": null, "ncols": null}}}