{"annotation": {"filename": "imagem-047.jpg", "folder": "segmentation_xray", "source": {"sourceImage": "The MIT-CSAIL database of objects and scenes", "sourceAnnotation": "LabelMe Webtool"}, "object": [{"name": "tooth", "deleted": "0", "verified": "0", "occluded": "no", "attributes": "18", "parts": {"hasparts": null, "ispartof": null}, "date": "14-12-21 21:47:59:392", "id": "0", "type": "bounding_box", "polygon": {"username": "anonymous", "pt": [{"x": "8", "y": "346", "time": "14-12-21 21:47:52:117"}, {"x": "222", "y": "346", "time": "14-12-21 21:47:55:100"}, {"x": "222", "y": "10", "time": "undefined"}, {"x": "8", "y": "10", "time": "undefined"}], "closed_date": "14-12-21 21:47:55:101"}}, {"name": "tooth", "deleted": "0", "verified": "0", "occluded": "no", "attributes": "17", "parts": {"hasparts": "11", "ispartof": null}, "date": "14-12-21 21:48:05:555", "id": "1", "type": "bounding_box", "polygon": {"username": "anonymous", "pt": [{"x": "144", "y": "486", "time": "14-12-21 21:48:00:582"}, {"x": "439", "y": "486", "time": "14-12-21 21:48:02:603"}, {"x": "439", "y": "0", "time": "undefined"}, {"x": "144", "y": "0", "time": "undefined"}], "closed_date": "14-12-21 21:48:02:604"}}, {"name": "tooth", "deleted": "0", "verified": "0", "occluded": "no", "attributes": "16", "parts": {"hasparts": "12", "ispartof": null}, "date": "14-12-21 21:48:12:992", "id": "2", "type": "bounding_box", "polygon": {"username": "anonymous", "pt": [{"x": "748", "y": "469", "time": "14-12-21 21:48:08:278"}, {"x": "432", "y": "469", "time": "14-12-21 21:48:09:981"}, {"x": "432", "y": "5", "time": "undefined"}, {"x": "748", "y": "5", "time": "undefined"}], "closed_date": "14-12-21 21:48:09:981"}}, {"name": "tooth", "deleted": "0", "verified": "0", "occluded": "no", "attributes": "15", "parts": {"hasparts": "13", "ispartof": null}, "date": "14-12-21 21:48:19:745", "id": "3", "type": "bounding_box", "polygon": {"username": "anonymous", "pt": [{"x": "967", "y": "441", "time": "14-12-21 21:48:14:597"}, {"x": "735", "y": "441", "time": "14-12-21 21:48:16:573"}, {"x": "735", "y": "7", "time": "undefined"}, {"x": "967", "y": "7", "time": "undefined"}], "closed_date": "14-12-21 21:48:16:573"}}, {"name": "tooth", "deleted": "0", "verified": "0", "occluded": "no", "attributes": "14", "parts": {"hasparts": null, "ispartof": null}, "date": "14-12-21 21:48:33:545", "id": "4", "type": "bounding_box", "polygon": {"username": "anonymous", "pt": [{"x": "1194", "y": "414", "time": "14-12-21 21:48:27:982"}, {"x": "920", "y": "414", "time": "14-12-21 21:48:29:925"}, {"x": "920", "y": "2", "time": "undefined"}, {"x": "1194", "y": "2", "time": "undefined"}], "closed_date": "14-12-21 21:48:29:925"}}, {"name": "tooth", "deleted": "0", "verified": "0", "occluded": "no", "attributes": "13", "parts": {"hasparts": null, "ispartof": null}, "date": "14-12-21 21:48:39:784", "id": "5", "type": "bounding_box", "polygon": {"username": "anonymous", "pt": [{"x": "1214", "y": "304", "time": "14-12-21 21:48:35:086"}, {"x": "1139", "y": "304", "time": "14-12-21 21:48:36:789"}, {"x": "1139", "y": "43", "time": "undefined"}, {"x": "1214", "y": "43", "time": "undefined"}], "closed_date": "14-12-21 21:48:36:789"}}, {"name": "tooth", "deleted": "0", "verified": "0", "occluded": "no", "attributes": "44", "parts": {"hasparts": null, "ispartof": null}, "date": "14-12-21 21:48:47:416", "id": "6", "type": "bounding_box", "polygon": {"username": "anonymous", "pt": [{"x": "1215", "y": "474", "time": "14-12-21 21:48:40:479"}, {"x": "1089", "y": "474", "time": "14-12-21 21:48:42:229"}, {"x": "1089", "y": "908", "time": "undefined"}, {"x": "1215", "y": "908", "time": "undefined"}], "closed_date": "14-12-21 21:48:42:229"}}, {"name": "tooth", "deleted": "0", "verified": "0", "occluded": "no", "attributes": "45", "parts": {"hasparts": "14", "ispartof": null}, "date": "14-12-21 21:48:56:079", "id": "7", "type": "bounding_box", "polygon": {"username": "anonymous", "pt": [{"x": "860", "y": "503", "time": "14-12-21 21:48:48:430"}, {"x": "1107", "y": "503", "time": "14-12-21 21:48:52:261"}, {"x": "1107", "y": "942", "time": "undefined"}, {"x": "860", "y": "942", "time": "undefined"}], "closed_date": "14-12-21 21:48:52:261"}}, {"name": "tooth", "deleted": "0", "verified": "0", "occluded": "no", "attributes": "46", "parts": {"hasparts": "15,16", "ispartof": null}, "date": "14-12-21 21:49:03:103", "id": "8", "type": "bounding_box", "polygon": {"username": "anonymous", "pt": [{"x": "554", "y": "521", "time": "14-12-21 21:48:56:902"}, {"x": "867", "y": "521", "time": "14-12-21 21:48:59:164"}, {"x": "867", "y": "945", "time": "undefined"}, {"x": "554", "y": "945", "time": "undefined"}], "closed_date": "14-12-21 21:48:59:165"}}, {"name": "tooth", "deleted": "0", "verified": "0", "occluded": "no", "attributes": "47", "parts": {"hasparts": "17", "ispartof": null}, "date": "14-12-21 21:49:10:312", "id": "9", "type": "bounding_box", "polygon": {"username": "anonymous", "pt": [{"x": "200", "y": "499", "time": "14-12-21 21:49:04:774"}, {"x": "551", "y": "499", "time": "14-12-21 21:49:06:164"}, {"x": "551", "y": "945", "time": "undefined"}, {"x": "200", "y": "945", "time": "undefined"}], "closed_date": "14-12-21 21:49:06:165"}}, {"name": "tooth", "deleted": "0", "verified": "0", "occluded": "no", "attributes": "48", "parts": {"hasparts": null, "ispartof": null}, "date": "14-12-21 21:49:17:665", "id": "10", "type": "bounding_box", "polygon": {"username": "anonymous", "pt": [{"x": "2", "y": "626", "time": "14-12-21 21:49:11:014"}, {"x": "215", "y": "626", "time": "14-12-21 21:49:13:389"}, {"x": "215", "y": "947", "time": "undefined"}, {"x": "2", "y": "947", "time": "undefined"}], "closed_date": "14-12-21 21:49:13:389"}}, {"name": "restoration", "deleted": "0", "verified": "0", "occluded": "no", "attributes": null, "parts": {"hasparts": null, "ispartof": "1"}, "date": "14-12-21 21:49:55:728", "id": "11", "polygon": {"username": "anonymous", "pt": [{"x": "232", "y": "282", "time": "14-12-21 21:49:41:630"}, {"x": "257", "y": "297", "time": "14-12-21 21:49:41:989"}, {"x": "272", "y": "322", "time": "14-12-21 21:49:42:278"}, {"x": "280", "y": "327", "time": "14-12-21 21:49:45:109"}, {"x": "287", "y": "319", "time": "14-12-21 21:49:45:412"}, {"x": "297", "y": "332", "time": "14-12-21 21:49:45:684"}, {"x": "317", "y": "347", "time": "14-12-21 21:49:45:956"}, {"x": "336", "y": "352", "time": "14-12-21 21:49:46:284"}, {"x": "337", "y": "371", "time": "14-12-21 21:49:46:541"}, {"x": "356", "y": "371", "time": "14-12-21 21:49:46:789"}, {"x": "376", "y": "367", "time": "14-12-21 21:49:47:004"}, {"x": "381", "y": "382", "time": "14-12-21 21:49:47:300"}, {"x": "397", "y": "387", "time": "14-12-21 21:49:47:596"}, {"x": "372", "y": "412", "time": "14-12-21 21:49:49:701"}, {"x": "344", "y": "412", "time": "14-12-21 21:49:50:061"}, {"x": "317", "y": "426", "time": "14-12-21 21:49:50:468"}, {"x": "294", "y": "414", "time": "14-12-21 21:49:50:917"}, {"x": "284", "y": "404", "time": "14-12-21 21:49:51:173"}, {"x": "262", "y": "404", "time": "14-12-21 21:49:51:397"}, {"x": "235", "y": "397", "time": "14-12-21 21:49:51:605"}, {"x": "219", "y": "396", "time": "14-12-21 21:49:51:821"}, {"x": "200", "y": "386", "time": "14-12-21 21:49:52:069"}, {"x": "192", "y": "376", "time": "14-12-21 21:49:52:309"}, {"x": "182", "y": "362", "time": "14-12-21 21:49:52:597"}, {"x": "182", "y": "346", "time": "14-12-21 21:49:52:877"}, {"x": "194", "y": "322", "time": "14-12-21 21:49:53:117"}, {"x": "210", "y": "309", "time": "14-12-21 21:49:53:341"}, {"x": "224", "y": "299", "time": "14-12-21 21:49:53:533"}], "closed_date": "14-12-21 21:49:53:782"}}, {"name": "restoration", "deleted": "0", "verified": "0", "occluded": "no", "attributes": null, "parts": {"hasparts": null, "ispartof": "2"}, "date": "14-12-21 21:50:08:519", "id": "12", "polygon": {"username": "anonymous", "pt": [{"x": "483", "y": "394", "time": "14-12-21 21:49:56:654"}, {"x": "483", "y": "369", "time": "14-12-21 21:49:57:005"}, {"x": "494", "y": "346", "time": "14-12-21 21:49:57:325"}, {"x": "506", "y": "331", "time": "14-12-21 21:49:57:685"}, {"x": "524", "y": "327", "time": "14-12-21 21:49:57:949"}, {"x": "548", "y": "334", "time": "14-12-21 21:49:58:189"}, {"x": "561", "y": "341", "time": "14-12-21 21:49:58:391"}, {"x": "579", "y": "342", "time": "14-12-21 21:49:58:613"}, {"x": "596", "y": "349", "time": "14-12-21 21:49:58:812"}, {"x": "613", "y": "357", "time": "14-12-21 21:49:59:045"}, {"x": "641", "y": "361", "time": "14-12-21 21:49:59:261"}, {"x": "659", "y": "374", "time": "14-12-21 21:49:59:493"}, {"x": "670", "y": "374", "time": "14-12-21 21:49:59:877"}, {"x": "651", "y": "337", "time": "14-12-21 21:50:00:652"}, {"x": "643", "y": "321", "time": "14-12-21 21:50:00:989"}, {"x": "643", "y": "297", "time": "14-12-21 21:50:01:261"}, {"x": "656", "y": "280", "time": "14-12-21 21:50:01:533"}, {"x": "676", "y": "270", "time": "14-12-21 21:50:01:765"}, {"x": "700", "y": "269", "time": "14-12-21 21:50:02:006"}, {"x": "723", "y": "269", "time": "14-12-21 21:50:02:228"}, {"x": "731", "y": "272", "time": "14-12-21 21:50:02:477"}, {"x": "740", "y": "291", "time": "14-12-21 21:50:02:726"}, {"x": "741", "y": "311", "time": "14-12-21 21:50:02:932"}, {"x": "745", "y": "339", "time": "14-12-21 21:50:03:186"}, {"x": "748", "y": "361", "time": "14-12-21 21:50:03:380"}, {"x": "748", "y": "366", "time": "14-12-21 21:50:03:604"}, {"x": "688", "y": "381", "time": "14-12-21 21:50:04:181"}, {"x": "658", "y": "394", "time": "14-12-21 21:50:04:542"}, {"x": "624", "y": "406", "time": "14-12-21 21:50:04:821"}, {"x": "598", "y": "407", "time": "14-12-21 21:50:05:093"}, {"x": "564", "y": "426", "time": "14-12-21 21:50:05:325"}, {"x": "548", "y": "447", "time": "14-12-21 21:50:05:573"}, {"x": "511", "y": "434", "time": "14-12-21 21:50:06:005"}, {"x": "483", "y": "412", "time": "14-12-21 21:50:06:316"}], "closed_date": "14-12-21 21:50:06:572"}}, {"name": "restoration", "deleted": "0", "verified": "0", "occluded": "no", "attributes": null, "parts": {"hasparts": null, "ispartof": "3"}, "date": "14-12-21 21:50:19:027", "id": "13", "polygon": {"username": "anonymous", "pt": [{"x": "803", "y": "357", "time": "14-12-21 21:50:11:807"}, {"x": "793", "y": "309", "time": "14-12-21 21:50:12:719"}, {"x": "788", "y": "291", "time": "14-12-21 21:50:13:197"}, {"x": "771", "y": "277", "time": "14-12-21 21:50:13:533"}, {"x": "748", "y": "280", "time": "14-12-21 21:50:13:869"}, {"x": "733", "y": "296", "time": "14-12-21 21:50:14:189"}, {"x": "733", "y": "332", "time": "14-12-21 21:50:14:550"}, {"x": "741", "y": "362", "time": "14-12-21 21:50:14:950"}, {"x": "758", "y": "376", "time": "14-12-21 21:50:15:285"}, {"x": "780", "y": "386", "time": "14-12-21 21:50:15:573"}, {"x": "791", "y": "387", "time": "14-12-21 21:50:15:837"}, {"x": "801", "y": "387", "time": "14-12-21 21:50:16:077"}, {"x": "813", "y": "377", "time": "14-12-21 21:50:16:325"}], "closed_date": "14-12-21 21:50:16:605"}}, {"name": "restoration", "deleted": "0", "verified": "0", "occluded": "no", "attributes": null, "parts": {"hasparts": null, "ispartof": "7"}, "date": "14-12-21 21:50:40:713", "id": "14", "polygon": {"username": "anonymous", "pt": [{"x": "1027", "y": "584", "time": "14-12-21 21:50:32:065"}, {"x": "1010", "y": "619", "time": "14-12-21 21:50:32:735"}, {"x": "992", "y": "634", "time": "14-12-21 21:50:33:165"}, {"x": "958", "y": "629", "time": "14-12-21 21:50:33:557"}, {"x": "943", "y": "616", "time": "14-12-21 21:50:33:909"}, {"x": "938", "y": "638", "time": "14-12-21 21:50:34:245"}, {"x": "938", "y": "646", "time": "14-12-21 21:50:34:453"}, {"x": "932", "y": "664", "time": "14-12-21 21:50:34:702"}, {"x": "915", "y": "668", "time": "14-12-21 21:50:35:102"}, {"x": "878", "y": "658", "time": "14-12-21 21:50:35:349"}, {"x": "873", "y": "648", "time": "14-12-21 21:50:35:621"}, {"x": "873", "y": "621", "time": "14-12-21 21:50:35:902"}, {"x": "873", "y": "586", "time": "14-12-21 21:50:36:182"}, {"x": "888", "y": "571", "time": "14-12-21 21:50:36:430"}, {"x": "903", "y": "566", "time": "14-12-21 21:50:36:645"}, {"x": "918", "y": "559", "time": "14-12-21 21:50:36:918"}, {"x": "953", "y": "559", "time": "14-12-21 21:50:37:158"}, {"x": "973", "y": "559", "time": "14-12-21 21:50:37:366"}, {"x": "997", "y": "556", "time": "14-12-21 21:50:37:597"}, {"x": "1022", "y": "554", "time": "14-12-21 21:50:37:885"}, {"x": "1049", "y": "566", "time": "14-12-21 21:50:38:112"}, {"x": "1040", "y": "584", "time": "14-12-21 21:50:38:349"}], "closed_date": "14-12-21 21:50:38:790"}}, {"name": "restoration", "deleted": "0", "verified": "0", "occluded": "no", "attributes": null, "parts": {"hasparts": null, "ispartof": "8"}, "date": "14-12-21 21:50:48:067", "id": "15", "polygon": {"username": "anonymous", "pt": [{"x": "786", "y": "613", "time": "14-12-21 21:50:41:591"}, {"x": "781", "y": "639", "time": "14-12-21 21:50:41:917"}, {"x": "788", "y": "671", "time": "14-12-21 21:50:42:398"}, {"x": "805", "y": "686", "time": "14-12-21 21:50:42:822"}, {"x": "826", "y": "693", "time": "14-12-21 21:50:43:192"}, {"x": "840", "y": "683", "time": "14-12-21 21:50:43:485"}, {"x": "853", "y": "668", "time": "14-12-21 21:50:43:775"}, {"x": "860", "y": "646", "time": "14-12-21 21:50:44:045"}, {"x": "865", "y": "614", "time": "14-12-21 21:50:44:309"}, {"x": "858", "y": "584", "time": "14-12-21 21:50:44:589"}, {"x": "841", "y": "568", "time": "14-12-21 21:50:44:893"}, {"x": "828", "y": "563", "time": "14-12-21 21:50:45:198"}, {"x": "800", "y": "563", "time": "14-12-21 21:50:45:462"}, {"x": "793", "y": "601", "time": "14-12-21 21:50:45:974"}], "closed_date": "14-12-21 21:50:46:270"}}, {"name": "restoration", "deleted": "0", "verified": "0", "occluded": "no", "attributes": null, "parts": {"hasparts": null, "ispartof": "8"}, "date": "14-12-21 21:50:57:442", "id": "16", "polygon": {"username": "anonymous", "pt": [{"x": "666", "y": "623", "time": "14-12-21 21:50:51:239"}, {"x": "693", "y": "623", "time": "14-12-21 21:50:51:526"}, {"x": "711", "y": "629", "time": "14-12-21 21:50:51:838"}, {"x": "726", "y": "628", "time": "14-12-21 21:50:52:101"}, {"x": "738", "y": "609", "time": "14-12-21 21:50:52:438"}, {"x": "755", "y": "608", "time": "14-12-21 21:50:52:694"}, {"x": "753", "y": "583", "time": "14-12-21 21:50:52:973"}, {"x": "748", "y": "576", "time": "14-12-21 21:50:53:253"}, {"x": "741", "y": "571", "time": "14-12-21 21:50:53:597"}, {"x": "713", "y": "573", "time": "14-12-21 21:50:53:862"}, {"x": "705", "y": "578", "time": "14-12-21 21:50:54:062"}, {"x": "690", "y": "566", "time": "14-12-21 21:50:54:373"}, {"x": "680", "y": "561", "time": "14-12-21 21:50:54:598"}, {"x": "663", "y": "566", "time": "14-12-21 21:50:54:790"}, {"x": "654", "y": "583", "time": "14-12-21 21:50:54:997"}, {"x": "653", "y": "601", "time": "14-12-21 21:50:55:206"}], "closed_date": "14-12-21 21:50:55:405"}}, {"name": "restoration", "deleted": "0", "verified": "0", "occluded": "no", "attributes": null, "parts": {"hasparts": null, "ispartof": "9"}, "date": "14-12-21 21:51:06:471", "id": "17", "polygon": {"username": "anonymous", "pt": [{"x": "262", "y": "613", "time": "14-12-21 21:50:58:111"}, {"x": "289", "y": "631", "time": "14-12-21 21:50:58:517"}, {"x": "326", "y": "636", "time": "14-12-21 21:50:58:910"}, {"x": "339", "y": "634", "time": "14-12-21 21:50:59:152"}, {"x": "361", "y": "638", "time": "14-12-21 21:50:59:350"}, {"x": "384", "y": "644", "time": "14-12-21 21:50:59:590"}, {"x": "411", "y": "646", "time": "14-12-21 21:50:59:783"}, {"x": "422", "y": "644", "time": "14-12-21 21:50:59:969"}, {"x": "446", "y": "633", "time": "14-12-21 21:51:00:169"}, {"x": "457", "y": "618", "time": "14-12-21 21:51:00:381"}, {"x": "469", "y": "601", "time": "14-12-21 21:51:00:621"}, {"x": "484", "y": "576", "time": "14-12-21 21:51:00:909"}, {"x": "478", "y": "561", "time": "14-12-21 21:51:01:293"}, {"x": "464", "y": "561", "time": "14-12-21 21:51:01:573"}, {"x": "436", "y": "576", "time": "14-12-21 21:51:01:813"}, {"x": "414", "y": "586", "time": "14-12-21 21:51:02:029"}, {"x": "394", "y": "594", "time": "14-12-21 21:51:02:220"}, {"x": "386", "y": "589", "time": "14-12-21 21:51:02:445"}, {"x": "381", "y": "568", "time": "14-12-21 21:51:02:845"}, {"x": "372", "y": "558", "time": "14-12-21 21:51:03:133"}, {"x": "352", "y": "558", "time": "14-12-21 21:51:03:357"}, {"x": "346", "y": "568", "time": "14-12-21 21:51:03:565"}, {"x": "341", "y": "574", "time": "14-12-21 21:51:03:748"}, {"x": "326", "y": "576", "time": "14-12-21 21:51:03:973"}, {"x": "307", "y": "578", "time": "14-12-21 21:51:04:165"}, {"x": "289", "y": "584", "time": "14-12-21 21:51:04:341"}, {"x": "267", "y": "588", "time": "14-12-21 21:51:04:549"}, {"x": "265", "y": "594", "time": "14-12-21 21:51:04:749"}], "closed_date": "14-12-21 21:51:04:949"}}], "imagesize": {"nrows": null, "ncols": null}}}