{"annotation": {"filename": "imagem-131.jpg", "folder": "segmentation_xray", "source": {"sourceImage": "The MIT-CSAIL database of objects and scenes", "sourceAnnotation": "LabelMe Webtool"}, "object": [{"name": "tooth", "deleted": "0", "verified": "0", "occluded": "no", "attributes": "27", "parts": {"hasparts": "10", "ispartof": null}, "date": "18-01-22 17:54:35:694", "id": "0", "type": "bounding_box", "polygon": {"username": "anonymous", "pt": [{"x": "1243", "y": "574", "time": "18-01-22 17:54:24:547"}, {"x": "1605", "y": "574", "time": "18-01-22 17:54:28:411"}, {"x": "1605", "y": "9", "time": "undefined"}, {"x": "1243", "y": "9", "time": "undefined"}], "closed_date": "18-01-22 17:54:28:411"}}, {"name": "tooth", "deleted": "0", "verified": "0", "occluded": "no", "attributes": "26", "parts": {"hasparts": "11,12", "ispartof": null}, "date": "18-01-22 17:54:43:764", "id": "1", "type": "bounding_box", "polygon": {"username": "anonymous", "pt": [{"x": "1237", "y": "578", "time": "18-01-22 17:54:36:812"}, {"x": "770", "y": "578", "time": "18-01-22 17:54:39:250"}, {"x": "770", "y": "13", "time": "undefined"}, {"x": "1237", "y": "13", "time": "undefined"}], "closed_date": "18-01-22 17:54:39:250"}}, {"name": "tooth", "deleted": "0", "verified": "0", "occluded": "no", "attributes": "25", "parts": {"hasparts": null, "ispartof": null}, "date": "18-01-22 17:54:52:012", "id": "2", "type": "bounding_box", "polygon": {"username": "anonymous", "pt": [{"x": "761", "y": "578", "time": "18-01-22 17:54:45:235"}, {"x": "473", "y": "578", "time": "18-01-22 17:54:48:402"}, {"x": "473", "y": "7", "time": "undefined"}, {"x": "761", "y": "7", "time": "undefined"}], "closed_date": "18-01-22 17:54:48:403"}}, {"name": "tooth", "deleted": "0", "verified": "0", "occluded": "no", "attributes": "24", "parts": {"hasparts": null, "ispartof": null}, "date": "18-01-22 17:55:01:516", "id": "3", "type": "bounding_box", "polygon": {"username": "anonymous", "pt": [{"x": "460", "y": "574", "time": "18-01-22 17:54:54:693"}, {"x": "174", "y": "574", "time": "18-01-22 17:54:58:145"}, {"x": "174", "y": "35", "time": "undefined"}, {"x": "460", "y": "35", "time": "undefined"}], "closed_date": "18-01-22 17:54:58:146"}}, {"name": "tooth", "deleted": "0", "verified": "0", "occluded": "no", "attributes": "23", "parts": {"hasparts": null, "ispartof": null}, "date": "18-01-22 17:55:08:127", "id": "4", "type": "bounding_box", "polygon": {"username": "anonymous", "pt": [{"x": "11", "y": "545", "time": "18-01-22 17:55:02:844"}, {"x": "270", "y": "545", "time": "18-01-22 17:55:04:146"}, {"x": "270", "y": "22", "time": "undefined"}, {"x": "11", "y": "22", "time": "undefined"}], "closed_date": "18-01-22 17:55:04:146"}}, {"name": "tooth", "deleted": "0", "verified": "0", "occluded": "no", "attributes": "33", "parts": {"hasparts": null, "ispartof": null}, "date": "18-01-22 17:55:20:244", "id": "5", "type": "bounding_box", "polygon": {"username": "anonymous", "pt": [{"x": "0", "y": "604", "time": "18-01-22 17:55:11:595"}, {"x": "266", "y": "604", "time": "18-01-22 17:55:14:010"}, {"x": "266", "y": "1237", "time": "undefined"}, {"x": "0", "y": "1237", "time": "undefined"}], "closed_date": "18-01-22 17:55:14:010"}}, {"name": "tooth", "deleted": "0", "verified": "0", "occluded": "no", "attributes": "34", "parts": {"hasparts": null, "ispartof": null}, "date": "18-01-22 17:55:29:866", "id": "6", "type": "bounding_box", "polygon": {"username": "anonymous", "pt": [{"x": "460", "y": "635", "time": "18-01-22 17:55:23:524"}, {"x": "153", "y": "635", "time": "18-01-22 17:55:25:746"}, {"x": "153", "y": "1224", "time": "undefined"}, {"x": "460", "y": "1224", "time": "undefined"}], "closed_date": "18-01-22 17:55:25:746"}}, {"name": "tooth", "deleted": "0", "verified": "0", "occluded": "no", "attributes": "36", "parts": {"hasparts": "13,14", "ispartof": null}, "date": "18-01-22 17:55:38:099", "id": "7", "type": "bounding_box", "polygon": {"username": "anonymous", "pt": [{"x": "757", "y": "648", "time": "18-01-22 17:55:31:483"}, {"x": "1285", "y": "648", "time": "18-01-22 17:55:34:155"}, {"x": "1285", "y": "1224", "time": "undefined"}, {"x": "757", "y": "1224", "time": "undefined"}], "closed_date": "18-01-22 17:55:34:156"}}, {"name": "tooth", "deleted": "0", "verified": "0", "occluded": "no", "attributes": "35", "parts": {"hasparts": null, "ispartof": null}, "date": "18-01-22 17:55:48:586", "id": "8", "type": "bounding_box", "polygon": {"username": "anonymous", "pt": [{"x": "829", "y": "1230", "time": "18-01-22 17:55:42:970"}, {"x": "430", "y": "1230", "time": "18-01-22 17:55:44:819"}, {"x": "430", "y": "665", "time": "undefined"}, {"x": "829", "y": "665", "time": "undefined"}], "closed_date": "18-01-22 17:55:44:819"}}, {"name": "tooth", "deleted": "0", "verified": "0", "occluded": "no", "attributes": "37", "parts": {"hasparts": null, "ispartof": null}, "date": "18-01-22 17:55:59:826", "id": "9", "type": "bounding_box", "polygon": {"username": "anonymous", "pt": [{"x": "1612", "y": "1186", "time": "18-01-22 17:55:53:395"}, {"x": "1234", "y": "1186", "time": "18-01-22 17:55:55:978"}, {"x": "1234", "y": "515", "time": "undefined"}, {"x": "1612", "y": "515", "time": "undefined"}], "closed_date": "18-01-22 17:55:55:978"}}, {"name": "restoration", "deleted": "0", "verified": "0", "occluded": "no", "attributes": null, "parts": {"hasparts": null, "ispartof": "0"}, "date": "18-01-22 17:56:55:900", "id": "10", "polygon": {"username": "anonymous", "pt": [{"x": "1383", "y": "449", "time": "18-01-22 17:56:44:877"}, {"x": "1374", "y": "390", "time": "18-01-22 17:56:45:315"}, {"x": "1370", "y": "336", "time": "18-01-22 17:56:45:610"}, {"x": "1381", "y": "299", "time": "18-01-22 17:56:45:882"}, {"x": "1381", "y": "260", "time": "18-01-22 17:56:46:210"}, {"x": "1391", "y": "225", "time": "18-01-22 17:56:46:490"}, {"x": "1426", "y": "196", "time": "18-01-22 17:56:46:771"}, {"x": "1479", "y": "196", "time": "18-01-22 17:56:47:058"}, {"x": "1501", "y": "196", "time": "18-01-22 17:56:47:322"}, {"x": "1525", "y": "192", "time": "18-01-22 17:56:47:570"}, {"x": "1566", "y": "212", "time": "18-01-22 17:56:47:890"}, {"x": "1594", "y": "297", "time": "18-01-22 17:56:48:714"}, {"x": "1601", "y": "371", "time": "18-01-22 17:56:49:362"}, {"x": "1564", "y": "410", "time": "18-01-22 17:56:49:996"}, {"x": "1514", "y": "447", "time": "18-01-22 17:56:50:394"}, {"x": "1487", "y": "454", "time": "18-01-22 17:56:50:658"}, {"x": "1457", "y": "454", "time": "18-01-22 17:56:50:906"}, {"x": "1405", "y": "460", "time": "18-01-22 17:56:51:170"}, {"x": "1394", "y": "462", "time": "18-01-22 17:56:51:571"}], "closed_date": "18-01-22 17:56:52:195"}}, {"name": "restoration", "deleted": "0", "verified": "0", "occluded": "no", "attributes": null, "parts": {"hasparts": null, "ispartof": "1"}, "date": "18-01-22 17:57:05:212", "id": "11", "polygon": {"username": "anonymous", "pt": [{"x": "907", "y": "445", "time": "18-01-22 17:56:57:595"}, {"x": "916", "y": "508", "time": "18-01-22 17:56:58:442"}, {"x": "949", "y": "508", "time": "18-01-22 17:56:58:978"}, {"x": "1001", "y": "519", "time": "18-01-22 17:56:59:578"}, {"x": "1021", "y": "519", "time": "18-01-22 17:56:59:923"}, {"x": "1034", "y": "504", "time": "18-01-22 17:57:00:314"}, {"x": "1023", "y": "447", "time": "18-01-22 17:57:00:970"}, {"x": "1010", "y": "432", "time": "18-01-22 17:57:01:658"}, {"x": "997", "y": "423", "time": "18-01-22 17:57:01:994"}, {"x": "977", "y": "423", "time": "18-01-22 17:57:02:226"}, {"x": "962", "y": "434", "time": "18-01-22 17:57:02:482"}, {"x": "942", "y": "443", "time": "18-01-22 17:57:02:802"}], "closed_date": "18-01-22 17:57:03:098"}}, {"name": "restoration", "deleted": "0", "verified": "0", "occluded": "no", "attributes": null, "parts": {"hasparts": null, "ispartof": "1"}, "date": "18-01-22 17:57:13:310", "id": "12", "polygon": {"username": "anonymous", "pt": [{"x": "1053", "y": "471", "time": "18-01-22 17:57:06:052"}, {"x": "1056", "y": "541", "time": "18-01-22 17:57:06:730"}, {"x": "1082", "y": "550", "time": "18-01-22 17:57:07:362"}, {"x": "1115", "y": "526", "time": "18-01-22 17:57:08:058"}, {"x": "1136", "y": "528", "time": "18-01-22 17:57:08:605"}, {"x": "1152", "y": "523", "time": "18-01-22 17:57:09:026"}, {"x": "1141", "y": "480", "time": "18-01-22 17:57:09:443"}, {"x": "1134", "y": "458", "time": "18-01-22 17:57:09:914"}, {"x": "1075", "y": "456", "time": "18-01-22 17:57:10:458"}, {"x": "1064", "y": "456", "time": "18-01-22 17:57:10:850"}], "closed_date": "18-01-22 17:57:11:162"}}, {"name": "restoration", "deleted": "0", "verified": "0", "occluded": "no", "attributes": null, "parts": {"hasparts": null, "ispartof": "7"}, "date": "18-01-22 17:57:28:861", "id": "13", "polygon": {"username": "anonymous", "pt": [{"x": "957", "y": "696", "time": "18-01-22 17:57:14:420"}, {"x": "955", "y": "720", "time": "18-01-22 17:57:14:819"}, {"x": "951", "y": "733", "time": "18-01-22 17:57:15:130"}, {"x": "944", "y": "748", "time": "18-01-22 17:57:15:420"}, {"x": "944", "y": "757", "time": "18-01-22 17:57:15:706"}, {"x": "964", "y": "768", "time": "18-01-22 17:57:16:003"}, {"x": "955", "y": "774", "time": "18-01-22 17:57:16:490"}, {"x": "931", "y": "783", "time": "18-01-22 17:57:20:810"}, {"x": "931", "y": "805", "time": "18-01-22 17:57:21:291"}, {"x": "957", "y": "818", "time": "18-01-22 17:57:21:658"}, {"x": "992", "y": "816", "time": "18-01-22 17:57:22:515"}, {"x": "1003", "y": "811", "time": "18-01-22 17:57:22:820"}, {"x": "1034", "y": "811", "time": "18-01-22 17:57:23:299"}, {"x": "1049", "y": "785", "time": "18-01-22 17:57:23:691"}, {"x": "1053", "y": "770", "time": "18-01-22 17:57:24:018"}, {"x": "1040", "y": "744", "time": "18-01-22 17:57:24:403"}, {"x": "1023", "y": "735", "time": "18-01-22 17:57:24:771"}, {"x": "1008", "y": "726", "time": "18-01-22 17:57:25:043"}, {"x": "999", "y": "713", "time": "18-01-22 17:57:25:307"}, {"x": "992", "y": "696", "time": "18-01-22 17:57:25:602"}, {"x": "975", "y": "691", "time": "18-01-22 17:57:25:875"}], "closed_date": "18-01-22 17:57:26:099"}}, {"name": "restoration", "deleted": "0", "verified": "0", "occluded": "no", "attributes": null, "parts": {"hasparts": null, "ispartof": "7"}, "date": "18-01-22 17:57:35:995", "id": "14", "polygon": {"username": "anonymous", "pt": [{"x": "1080", "y": "702", "time": "18-01-22 17:57:29:724"}, {"x": "1080", "y": "742", "time": "18-01-22 17:57:30:098"}, {"x": "1069", "y": "763", "time": "18-01-22 17:57:30:635"}, {"x": "1088", "y": "772", "time": "18-01-22 17:57:31:018"}, {"x": "1112", "y": "772", "time": "18-01-22 17:57:31:347"}, {"x": "1138", "y": "772", "time": "18-01-22 17:57:31:610"}, {"x": "1143", "y": "755", "time": "18-01-22 17:57:32:147"}, {"x": "1121", "y": "737", "time": "18-01-22 17:57:32:539"}, {"x": "1119", "y": "707", "time": "18-01-22 17:57:32:859"}], "closed_date": "18-01-22 17:57:33:197"}}], "imagesize": {"nrows": null, "ncols": null}}}